showcues.py
showcues-1.0.43.data/scripts/showcues
showcues-1.0.43.dist-info/LICENSE
showcues-1.0.43.dist-info/METADATA
showcues-1.0.43.dist-info/WHEEL
showcues-1.0.43.dist-info/top_level.txt
showcues-1.0.43.dist-info/RECORD
