Metadata-Version: 2.1
Name: showcues
Version: 1.0.43
Summary: showcues is a HLS SCTE-35 debugger and manifest manipulator
Home-page: https://github.com/futzu/showcues
Author: Adrian of Doom.
Author-email: spam@iodisco.com
Platform: all
Classifier: License :: OSI Approved :: MIT License
Classifier: Operating System :: OS Independent
Classifier: Programming Language :: Python :: 3.6
Classifier: Programming Language :: Python :: Implementation :: PyPy
Classifier: Programming Language :: Python :: Implementation :: CPython
Requires-Python: >=3.6
License-File: LICENSE
Requires-Dist: m3ufu (>=0.0.89)
Requires-Dist: new-reader (>=0.1.7)
Requires-Dist: threefive (>=2.4.35)
